supervisor/__init__.py
supervisor/example.py
supervisor/message_handlers.py
supervisor/models.py
supervisor/version.py
agrc_supervisor-3.1.0.dist-info/LICENSE
agrc_supervisor-3.1.0.dist-info/METADATA
agrc_supervisor-3.1.0.dist-info/WHEEL
agrc_supervisor-3.1.0.dist-info/top_level.txt
agrc_supervisor-3.1.0.dist-info/zip-safe
agrc_supervisor-3.1.0.dist-info/RECORD
